aopp_deconv_tool/__init__.py
aopp_deconv_tool/arguments.py
aopp_deconv_tool/artefact_detection.py
aopp_deconv_tool/cast.py
aopp_deconv_tool/create_bad_pixel_mask.py
aopp_deconv_tool/deconvolve.py
aopp_deconv_tool/estimate_noise.py
aopp_deconv_tool/extract_sources.py
aopp_deconv_tool/fit_psf_model.py
aopp_deconv_tool/fits_copy_wcs.py
aopp_deconv_tool/fits_slice.py
aopp_deconv_tool/fpath.py
aopp_deconv_tool/geo_array.py
aopp_deconv_tool/interpolate.py
aopp_deconv_tool/mfunc.py
aopp_deconv_tool/psf_data_ops.py
aopp_deconv_tool/psf_normalise.py
aopp_deconv_tool/py_ssa.py
aopp_deconv_tool/py_svd.py
aopp_deconv_tool/spatial_rebin.py
aopp_deconv_tool/spectral_rebin.py
aopp_deconv_tool/task_strat.py
aopp_deconv_tool/to_fits.py
aopp_deconv_tool/typedef.py
aopp_deconv_tool/algorithm/__init__.py
aopp_deconv_tool/algorithm/artefact_detection/__init__.py
aopp_deconv_tool/algorithm/bad_pixels/__init__.py
aopp_deconv_tool/algorithm/bad_pixels/ssa_sum_prob.py
aopp_deconv_tool/algorithm/deconv/__init__.py
aopp_deconv_tool/algorithm/deconv/base.py
aopp_deconv_tool/algorithm/deconv/clean_modified.py
aopp_deconv_tool/algorithm/deconv/lucy_richardson.py
aopp_deconv_tool/algorithm/interpolate/__init__.py
aopp_deconv_tool/algorithm/interpolate/ssa_interp.py
aopp_deconv_tool/astropy_helper/__init__.py
aopp_deconv_tool/astropy_helper/fits/__init__.py
aopp_deconv_tool/astropy_helper/fits/header.py
aopp_deconv_tool/astropy_helper/fits/specifier.py
aopp_deconv_tool/cfg/__init__.py
aopp_deconv_tool/cfg/logs.py
aopp_deconv_tool/cfg/settings.py
aopp_deconv_tool/context/__init__.py
aopp_deconv_tool/context/alias.py
aopp_deconv_tool/context/next.py
aopp_deconv_tool/context/temp.py
aopp_deconv_tool/data_structures/__init__.py
aopp_deconv_tool/data_structures/bi_directional_map.py
aopp_deconv_tool/data_structures/pointer.py
aopp_deconv_tool/geometry/__init__.py
aopp_deconv_tool/geometry/bounding_box.py
aopp_deconv_tool/geometry/shape/__init__.py
aopp_deconv_tool/graphical_frontends/__init__.py
aopp_deconv_tool-0.1.28.dist-info/METADATA
aopp_deconv_tool-0.1.28.dist-info/WHEEL
aopp_deconv_tool-0.1.28.dist-info/top_level.txt
aopp_deconv_tool-0.1.28.dist-info/RECORD
