Metadata-Version: 2.1
Name: aopp_deconv_tool
Version: 0.1.28
Summary: Tool for performing deconvolution (using LucyRichardson and ModifiedClean algorithms), PSF fitting and filtering, and data manipulation for 2d images and 3d datacubes.
Author-email: Jack Dobinson <jack.dobinson@physics.ox.ac.uk>
Keywords: deconvolution,ModifiedClean
Classifier: License :: OSI Approved :: MIT License
Classifier: Programming Language :: Python :: 3.12
Classifier: Development Status :: 3 - Alpha
Classifier: Environment :: Console
Classifier: Intended Audience :: Science/Research
Classifier: Natural Language :: English
Classifier: Operating System :: Unix
Classifier: Operating System :: Microsoft :: Windows
Classifier: Topic :: Scientific/Engineering :: Image Processing
Classifier: Topic :: Scientific/Engineering :: Astronomy
Requires-Python: >=3.12
Requires-Dist: numpy
Requires-Dist: astropy
Requires-Dist: scipy
Requires-Dist: matplotlib
Requires-Dist: ultranest
Requires-Dist: h5py
Requires-Dist: scikit-image
Requires-Dist: regions
